{
    "points": [
        {
            "x": 191,
            "y": 199
        },
        {
            "x": 656,
            "y": 243
        },
        {
            "x": 536,
            "y": 469
        },
        {
            "x": 140,
            "y": 355
        }
    ],
    "lines": [
        {
            "pt1": {
                "x": 191,
                "y": 199
            },
            "pt2": {
                "x": 656,
                "y": 243
            }
        },
        {
            "pt1": {
                "x": 536,
                "y": 469
            },
            "pt2": {
                "x": 656,
                "y": 243
            }
        },
        {
            "pt1": {
                "x": 140,
                "y": 355
            },
            "pt2": {
                "x": 656,
                "y": 243
            }
        }
    ]
}